LICENSE
README.md
setup.cfg
setup.py
HierarchiaPy/HierarchiaPy.py
HierarchiaPy/__init__.py
HierarchiaPy.egg-info/PKG-INFO
HierarchiaPy.egg-info/SOURCES.txt
HierarchiaPy.egg-info/dependency_links.txt
HierarchiaPy.egg-info/requires.txt
HierarchiaPy.egg-info/top_level.txt
HierarchiaPy/methods/_ISI98.py
HierarchiaPy/methods/_adagio.py
HierarchiaPy/methods/_average_dominance_index.py
HierarchiaPy/methods/_davids_score.py
HierarchiaPy/methods/_elo.py
HierarchiaPy/methods/_randomized_elo.py
HierarchiaPy/metrics/_dci.py
HierarchiaPy/metrics/_kendall_k.py
HierarchiaPy/metrics/_landau_h.py
HierarchiaPy/metrics/_steepness.py
HierarchiaPy/utilities/_network_graph.py
tests/test_linearity.py
tests/test_network_vizualization.py
tests/test_steepness.py