Metadata-Version: 2.1
Name: HierarchiaPy
Version: 0.2.6
Summary: HierarchiaPy: statistical package to derive hiearchy from social interactions
Home-page: https://github.com/nusretipek/HierarchiaPy
Download-URL: https://github.com/nusretipek/HierarchiaPy
Author: Nusret Ipek
Author-email: Nusret.Ipek@UGent.be
License: MIT
Classifier: Development Status :: 4 - Beta
Classifier: Programming Language :: Python :: 3
Classifier: Programming Language :: Python :: 3 :: Only
Classifier: Programming Language :: Python :: 3.7
Classifier: Programming Language :: Python :: 3.8
Classifier: Programming Language :: Python :: 3.9
Classifier: License :: OSI Approved :: MIT License
Classifier: Topic :: Sociology
Classifier: Intended Audience :: Science/Research
Classifier: Operating System :: Microsoft :: Windows
Classifier: Operating System :: Unix
Classifier: Operating System :: MacOS
License-File: LICENSE
